python_plc_simulator/__init__.py
python_plc_simulator/logger/__init__.py
python_plc_simulator/logger/const.py
python_plc_simulator/logger/file_formatter.py
python_plc_simulator/logger/logger.py
python_plc_simulator/logger/stream_formatter.py
python_plc_simulator/modbus_client/__init__.py
python_plc_simulator/modbus_client/exceptions.py
python_plc_simulator/modbus_client/modbus_client.py
python_plc_simulator/models/__init__.py
python_plc_simulator/models/device_configuration_base.py
python_plc_simulator/models/devices/__init__.py
python_plc_simulator/models/devices/device_base.py
python_plc_simulator/models/devices/siemens_cpu1212.py
python_plc_simulator/models/register.py
python_plc_simulator/models/signal_bool.py
python_plc_simulator-0.0.1.dist-info/METADATA
python_plc_simulator-0.0.1.dist-info/WHEEL
python_plc_simulator-0.0.1.dist-info/RECORD
