Metadata-Version: 2.1
Name: python-plc-simulator
Version: 0.0.1
Summary: 
Author: Konstantin.Dudersky
Author-email: konstantin.dudersky@gmail.com
Requires-Python: >=3.11,<4.0
Classifier: Programming Language :: Python :: 3
Classifier: Programming Language :: Python :: 3.11
Requires-Dist: async-state-machine (==0.0.2)
Requires-Dist: pymodbus (>=3.2.2,<4.0.0)
